isp_table_configs/6.0/affine_heat_rates.yaml
isp_table_configs/6.0/aggregated_energy_storages.yaml
isp_table_configs/6.0/assumptions_summary.yaml
isp_table_configs/6.0/auxiliary.yaml
isp_table_configs/6.0/battery_&_plug-in_evs.yaml
isp_table_configs/6.0/build_costs.yaml
isp_table_configs/6.0/build_costs_pem.yaml
isp_table_configs/6.0/build_limits.yaml
isp_table_configs/6.0/build_limits_phes.yaml
isp_table_configs/6.0/capacity_factors.yaml
isp_table_configs/6.0/carbon_budgets.yaml
isp_table_configs/6.0/ccgt_unit_max_capacity.yaml
isp_table_configs/6.0/change_log.yaml
isp_table_configs/6.0/coal_and_biomass_price.yaml
isp_table_configs/6.0/connection_cost.yaml
isp_table_configs/6.0/connection_costs_forecast.yaml
isp_table_configs/6.0/costs_summary_pem.yaml
isp_table_configs/6.0/demand_and_energy_forecasts.yaml
isp_table_configs/6.0/disclaimer.yaml
isp_table_configs/6.0/dsp.yaml
isp_table_configs/6.0/economic_growth_forecasts.yaml
isp_table_configs/6.0/electrification.yaml
isp_table_configs/6.0/embedded_energy_storages.yaml
isp_table_configs/6.0/emissions_intensity.yaml
isp_table_configs/6.0/energy_efficiency.yaml
isp_table_configs/6.0/energy_policy_targets.yaml
isp_table_configs/6.0/ev_v2g.yaml
isp_table_configs/6.0/existing_gen_data_summary.yaml
isp_table_configs/6.0/financial_parameters.yaml
isp_table_configs/6.0/fixed_opex.yaml
isp_table_configs/6.0/flow_path_augmentation_options.yaml
isp_table_configs/6.0/flow_path_costs_forecast.yaml
isp_table_configs/6.0/fuel_cell_evs.yaml
isp_table_configs/6.0/fuel_price_summary.yaml
isp_table_configs/6.0/gas_liquid_fuel_h2_price.yaml
isp_table_configs/6.0/generation_limits.yaml
isp_table_configs/6.0/generator_reliability_settings.yaml
isp_table_configs/6.0/gpg_emissions_reduction_biom.yaml
isp_table_configs/6.0/gpg_min_stable_level.yaml
isp_table_configs/6.0/h2_gpg_emissions_reduction_.yaml
isp_table_configs/6.0/heat_rates.yaml
isp_table_configs/6.0/hydro_climate_factor.yaml
isp_table_configs/6.0/hydro_scheme_inflows.yaml
isp_workbook_parser-2.7.0.dist-info/licenses/LICENSE
isp_workbook_parser-2.7.0.dist-info/METADATA
isp_workbook_parser-2.7.0.dist-info/WHEEL
isp_workbook_parser-2.7.0.dist-info/top_level.txt
isp_workbook_parser-2.7.0.dist-info/RECORD
