Metadata-Version: 2.4
Name: isp-workbook-parser
Version: 2.7.0
Summary: A Python package for reading data from the Inputs, Assumptions and Scenarios Report (IASR) Microsoft Excel workbook published by the Australian Energy Market Operator for use in their Integrated System Plan modelling.
Author-email: nick-gorman <n.gorman305@gmail.com>, prakaa <abiprakash007@gmail.com>, dylanjmcconnell <dylan.mcconnell@unsw.edu.au>
Requires-Python: >=3.9
License-File: LICENSE
Requires-Dist: pandas>=2.2.2
Requires-Dist: openpyxl>=3.1.5
Requires-Dist: pydantic>=2.8.2
Requires-Dist: pyyaml>=6.0.1
Requires-Dist: thefuzz>=0.22.1
Dynamic: license-file
